spotipython/__init__.py
spotipython/api/__init__.py
spotipython/api/albums/__init__.py
spotipython/api/albums/check_users_saved_albums.py
spotipython/api/albums/get_an_album.py
spotipython/api/albums/get_an_albums_tracks.py
spotipython/api/albums/get_multiple_albums.py
spotipython/api/albums/get_new_releases.py
spotipython/api/albums/get_users_saved_albums.py
spotipython/api/albums/remove_albums_user.py
spotipython/api/albums/save_albums_user.py
spotipython/api/artists/__init__.py
spotipython/api/artists/get_an_artist.py
spotipython/api/artists/get_an_artists_albums.py
spotipython/api/artists/get_an_artists_related_artists.py
spotipython/api/artists/get_an_artists_top_tracks.py
spotipython/api/artists/get_multiple_artists.py
spotipython/api/audiobooks/__init__.py
spotipython/api/audiobooks/check_users_saved_audiobooks.py
spotipython/api/audiobooks/get_an_audiobook.py
spotipython/api/audiobooks/get_audiobook_chapters.py
spotipython/api/audiobooks/get_multiple_audiobooks.py
spotipython/api/audiobooks/get_users_saved_audiobooks.py
spotipython/api/audiobooks/remove_audiobooks_user.py
spotipython/api/audiobooks/save_audiobooks_user.py
spotipython/api/categories/__init__.py
spotipython/api/categories/get_a_category.py
spotipython/api/categories/get_categories.py
spotipython/api/chapters/__init__.py
spotipython/api/chapters/get_a_chapter.py
spotipython/api/chapters/get_several_chapters.py
spotipython/api/episodes/__init__.py
spotipython/api/episodes/check_users_saved_episodes.py
spotipython/api/episodes/get_an_episode.py
spotipython/api/episodes/get_multiple_episodes.py
spotipython/api/episodes/get_users_saved_episodes.py
spotipython/api/episodes/remove_episodes_user.py
spotipython/api/episodes/save_episodes_user.py
spotipython/api/genres/__init__.py
spotipython/api/genres/get_recommendation_genres.py
spotipython/api/markets/__init__.py
spotipython/api/markets/get_available_markets.py
spotipython/api/player/__init__.py
spotipython/api/player/add_to_queue.py
spotipython-0.1.2.post0.dist-info/licenses/LICENCE
spotipython-0.1.2.post0.dist-info/WHEEL
spotipython-0.1.2.post0.dist-info/METADATA
spotipython-0.1.2.post0.dist-info/RECORD
