Metadata-Version: 2.4
Name: spotipython
Version: 0.1.2.post0
Summary: Autogenerated Spotify Web API client library. Supports async and typed.
Author: Maurice Banerjee Palmer
Author-email: Maurice Banerjee Palmer <spotipython@maurice.fm>
License-Expression: MIT
License-File: LICENCE
Classifier: Programming Language :: Python :: 3
Classifier: Operating System :: OS Independent
Classifier: License :: OSI Approved :: MIT License
Requires-Dist: attrs>=25.3.0
Requires-Dist: httpx>=0.28.1
Requires-Dist: python-dateutil>=2.9.0.post0
Requires-Dist: python-dotenv>=1.1.1
Requires-Python: >=3.13
Project-URL: Homepage, https://github.com/mbanerjeepalmer/spotipython
